asyncdagpi/__init__.py
asyncdagpi/client.py
asyncdagpi/errors.py
asyncdagpi/http.py
asyncdagpi/image.py
asyncdagpi/image_features.py
asyncdagpi/objects.py
asyncdagpi/py.typed
asyncdagpi-4.1.3.dist-info/LICENSE
asyncdagpi-4.1.3.dist-info/WHEEL
asyncdagpi-4.1.3.dist-info/METADATA
asyncdagpi-4.1.3.dist-info/RECORD
