Metadata-Version: 2.1
Name: asyncdagpi
Version: 4.1.3
Summary: An Asynchronos API wrapper for https://dagpi.xyz
Home-page: https://github.com/Daggy1234/asyncdagpi
License: MIT
Author: Daggy1234
Author-email: daggy@daggy.tech
Requires-Python: >=3.8,<4.0
Classifier: License :: OSI Approved :: MIT License
Classifier: Programming Language :: Python :: 3
Classifier: Programming Language :: Python :: 3.10
Classifier: Programming Language :: Python :: 3.8
Classifier: Programming Language :: Python :: 3.9
Requires-Dist: aiohttp (>=3.7.3,<4.0.0)
Project-URL: Repository, https://github.com/Daggy1234/asyncdagpi
